BL_Python/__init__.py
BL_Python/AWS/__init__.py
BL_Python/AWS/py.typed
BL_Python/AWS/ssm.py
BL_Python/GitHub/__init__.py
BL_Python/GitHub/api.py
BL_Python/GitHub/py.typed
BL_Python/database/__init__.py
BL_Python/database/config.py
BL_Python/database/dependency_injection.py
BL_Python/database/py.typed
BL_Python/database/types.py
BL_Python/development/__init__.py
BL_Python/development/profiling.py
BL_Python/development/py.typed
BL_Python/identity/__init__.py
BL_Python/identity/config.py
BL_Python/identity/dependency_injection.py
BL_Python/identity/py.typed
BL_Python/platform/__init__.py
BL_Python/platform/dependency_injection.py
BL_Python/platform/py.typed
BL_Python/programming/__init__.py
BL_Python/programming/dependency_injection.py
BL_Python/programming/py.typed
BL_Python/testing/__init__.py
BL_Python/testing/py.typed
BL_Python/web/__init__.py
BL_Python/web/application.py
BL_Python/web/config.py
BL_Python/web/py.typed
BL_Python.all-0.3.0.dist-info/LICENSE.md
BL_Python.all-0.3.0.dist-info/METADATA
BL_Python.all-0.3.0.dist-info/WHEEL
BL_Python.all-0.3.0.dist-info/top_level.txt
BL_Python.all-0.3.0.dist-info/RECORD
