Metadata-Version: 2.1
Name: BL_Python.all
Version: 0.3.0
Summary: Python libraries for use in Boutros Lab.
Author-email: Aaron Holmes <aholmes@mednet.ucla.edu>
Project-URL: Homepage, https://github.com/uclahs-cds/BL_Python
Project-URL: Bug Tracker, https://github.com/uclahs-cds/BL_Python/issues
Project-URL: Repository, https://github.com/uclahs-cds/BL_Python.git
Project-URL: Changelog, https://github.com/uclahs-cds/BL_Python/blob/main/CHANGELOG.md
Classifier: Programming Language :: Python :: 3
Classifier: License :: OSI Approved :: GNU General Public License (GPL)
Classifier: Operating System :: OS Independent
Classifier: Topic :: Scientific/Engineering
Classifier: Topic :: Software Development :: Libraries
Classifier: Topic :: Software Development :: Libraries :: Application Frameworks
Classifier: Intended Audience :: Science/Research
Classifier: Intended Audience :: Developers
Classifier: Development Status :: 4 - Beta
Classifier: Natural Language :: English
Requires-Python: >=3.10
License-File: LICENSE.md
Requires-Dist: BL-Python.AWS
Requires-Dist: BL-Python.database
Requires-Dist: BL-Python.development
Requires-Dist: BL-Python.GitHub
Requires-Dist: BL-Python.identity
Requires-Dist: BL-Python.platform
Requires-Dist: BL-Python.programming
Requires-Dist: BL-Python.testing
Requires-Dist: BL-Python.web
Provides-Extra: dev-dependencies
Requires-Dist: pytest~=8.0; extra == "dev-dependencies"
Requires-Dist: pytest-mock; extra == "dev-dependencies"
Requires-Dist: mock; extra == "dev-dependencies"
Requires-Dist: pytest-cov<5.0,>=4.1; extra == "dev-dependencies"
Requires-Dist: coverage~=7.4; extra == "dev-dependencies"
Requires-Dist: junit2html<32.0,>=30.1; extra == "dev-dependencies"
Requires-Dist: pyright==1.1.375; extra == "dev-dependencies"
Requires-Dist: isort~=5.13; extra == "dev-dependencies"
Requires-Dist: ruff~=0.3; extra == "dev-dependencies"
Requires-Dist: bandit[sarif,toml]~=1.7; extra == "dev-dependencies"
